ruri/__init__.py
ruri/__main__.py
ruri/assistant.py
ruri/crc32.py
ruri/ruri.py
ruri/vars.py
ruri-1.2.0.dist-info/METADATA
ruri-1.2.0.dist-info/WHEEL
ruri-1.2.0.dist-info/entry_points.txt
ruri-1.2.0.dist-info/top_level.txt
ruri-1.2.0.dist-info/RECORD
