Metadata-Version: 2.1
Name: ruri
Version: 1.2.0
Summary: A CRC32 checker with file name checking.
Home-page: https://gitlab.com/Timmy1e/ruri
Author: Tim van Leuverden
Author-email: TvanLeuverden@Gmail.com
License: GPL-3
Platform: UNKNOWN
Classifier: Development Status :: 5 - Production/Stable
Classifier: Environment :: Console
Classifier: Programming Language :: Python :: 3
Classifier: License :: OSI Approved :: GNU General Public License v3 or later (GPLv3+)
Classifier: Operating System :: OS Independent
